{
  "origin": "codeshovel",
  "repositoryName": "hadoop",
  "repositoryPath": "/home/shaiful/research/codeshovel/codeshovel-projects/hadoop/.git",
  "startCommitName": "HEAD",
  "sourceFileName": "Merger.java",
  "functionName": "resetKeyValue",
  "functionId": "resetKeyValue",
  "sourceFilePath": "hadoop-mapreduce-project/hadoop-mapreduce-client/hadoop-mapreduce-client-core/src/main/java/org/apache/hadoop/mapred/Merger.java",
  "functionStartLine": 531,
  "functionEndLine": 535,
  "numCommitsSeen": 12,
  "timeTaken": 758,
  "changeHistory": [
    "90194ca1cbd695d48c3705121c2ac9a8554578a2"
  ],
  "changeHistoryShort": {
    "90194ca1cbd695d48c3705121c2ac9a8554578a2": "Yintroduced"
  },
  "changeHistoryDetails": {
    "90194ca1cbd695d48c3705121c2ac9a8554578a2": {
      "type": "Yintroduced",
      "commitMessage": "MAPREDUCE-6169. MergeQueue should release reference to the current item from key and value at the end of the iteration to save memory. (Zhihai Xu via kasha)\n",
      "commitDate": "20/11/14 3:36 PM",
      "commitName": "90194ca1cbd695d48c3705121c2ac9a8554578a2",
      "commitAuthor": "Karthik Kambatla",
      "diff": "@@ -0,0 +1,5 @@\n+    private void resetKeyValue() {\n+      key \u003d null;\n+      value.reset(new byte[] {}, 0);\n+      diskIFileValue.reset(new byte[] {}, 0);\n+    }\n\\ No newline at end of file\n",
      "actualSource": "    private void resetKeyValue() {\n      key \u003d null;\n      value.reset(new byte[] {}, 0);\n      diskIFileValue.reset(new byte[] {}, 0);\n    }",
      "path": "hadoop-mapreduce-project/hadoop-mapreduce-client/hadoop-mapreduce-client-core/src/main/java/org/apache/hadoop/mapred/Merger.java"
    }
  }
}