{
  "origin": "codeshovel",
  "repositoryName": "hadoop",
  "repositoryPath": "/home/shaiful/research/codeshovel/codeshovel-projects/hadoop/.git",
  "startCommitName": "HEAD",
  "sourceFileName": "WebHdfsFileSystem.java",
  "functionName": "setErasureCodingPolicy",
  "functionId": "setErasureCodingPolicy___p-Path__policyName-String",
  "sourceFilePath": "hadoop-hdfs-project/hadoop-hdfs-client/src/main/java/org/apache/hadoop/hdfs/web/WebHdfsFileSystem.java",
  "functionStartLine": 1354,
  "functionEndLine": 1360,
  "numCommitsSeen": 73,
  "timeTaken": 1308,
  "changeHistory": [
    "39dc7345b80e27ba8bd1ff4c19ca241aef5ac0fc"
  ],
  "changeHistoryShort": {
    "39dc7345b80e27ba8bd1ff4c19ca241aef5ac0fc": "Yintroduced"
  },
  "changeHistoryDetails": {
    "39dc7345b80e27ba8bd1ff4c19ca241aef5ac0fc": {
      "type": "Yintroduced",
      "commitMessage": "HDFS-14124. EC : Support EC Commands (set/get/unset EcPolicy) via WebHdfs. Contributed by Ayush Saxena.\n",
      "commitDate": "11/12/18 4:29 AM",
      "commitName": "39dc7345b80e27ba8bd1ff4c19ca241aef5ac0fc",
      "commitAuthor": "Vinayakumar B",
      "diff": "@@ -0,0 +1,7 @@\n+  public void setErasureCodingPolicy(Path p, String policyName)\n+      throws IOException {\n+    statistics.incrementWriteOps(1);\n+    storageStatistics.incrementOpCounter(OpType.SET_EC_POLICY);\n+    final HttpOpParam.Op op \u003d PutOpParam.Op.SETECPOLICY;\n+    new FsPathRunner(op, p, new ECPolicyParam(policyName)).run();\n+  }\n\\ No newline at end of file\n",
      "actualSource": "  public void setErasureCodingPolicy(Path p, String policyName)\n      throws IOException {\n    statistics.incrementWriteOps(1);\n    storageStatistics.incrementOpCounter(OpType.SET_EC_POLICY);\n    final HttpOpParam.Op op \u003d PutOpParam.Op.SETECPOLICY;\n    new FsPathRunner(op, p, new ECPolicyParam(policyName)).run();\n  }",
      "path": "hadoop-hdfs-project/hadoop-hdfs-client/src/main/java/org/apache/hadoop/hdfs/web/WebHdfsFileSystem.java"
    }
  }
}