{
  "origin": "codeshovel",
  "repositoryName": "hadoop",
  "repositoryPath": "/home/shaiful/research/codeshovel/codeshovel-projects/hadoop/.git",
  "startCommitName": "HEAD",
  "sourceFileName": "WebHdfsFileSystem.java",
  "functionName": "createWrappedInputStream",
  "functionId": "createWrappedInputStream",
  "sourceFilePath": "hadoop-hdfs-project/hadoop-hdfs-client/src/main/java/org/apache/hadoop/hdfs/web/WebHdfsFileSystem.java",
  "functionStartLine": 2196,
  "functionEndLine": 2199,
  "numCommitsSeen": 73,
  "timeTaken": 1778,
  "changeHistory": [
    "fde95d463c3123b315b3d07cb5b7b7dc19f7cb73"
  ],
  "changeHistoryShort": {
    "fde95d463c3123b315b3d07cb5b7b7dc19f7cb73": "Yintroduced"
  },
  "changeHistoryDetails": {
    "fde95d463c3123b315b3d07cb5b7b7dc19f7cb73": {
      "type": "Yintroduced",
      "commitMessage": "HDFS-12574. Add CryptoInputStream to WebHdfsFileSystem read call. Contributed by Rushabh S Shah\n",
      "commitDate": "29/01/18 3:23 PM",
      "commitName": "fde95d463c3123b315b3d07cb5b7b7dc19f7cb73",
      "commitAuthor": "Kihwal Lee",
      "diff": "@@ -0,0 +1,4 @@\n+    InputStream createWrappedInputStream() throws IOException {\n+      return HdfsKMSUtil.createWrappedInputStream(\n+          this, getKeyProvider(), getFileEncryptionInfo(), getConf());\n+    }\n\\ No newline at end of file\n",
      "actualSource": "    InputStream createWrappedInputStream() throws IOException {\n      return HdfsKMSUtil.createWrappedInputStream(\n          this, getKeyProvider(), getFileEncryptionInfo(), getConf());\n    }",
      "path": "hadoop-hdfs-project/hadoop-hdfs-client/src/main/java/org/apache/hadoop/hdfs/web/WebHdfsFileSystem.java"
    }
  }
}