{
  "origin": "codeshovel",
  "repositoryName": "hadoop",
  "repositoryPath": "/home/shaiful/research/codeshovel/codeshovel-projects/hadoop/.git",
  "startCommitName": "HEAD",
  "sourceFileName": "ResourceManager.java",
  "functionName": "printUsage",
  "functionId": "printUsage___out-PrintStream",
  "sourceFilePath": "hadoop-yarn-project/hadoop-yarn/hadoop-yarn-server/hadoop-yarn-server-resourcemanager/src/main/java/org/apache/hadoop/yarn/server/resourcemanager/ResourceManager.java",
  "functionStartLine": 1721,
  "functionEndLine": 1728,
  "numCommitsSeen": 192,
  "timeTaken": 5001,
  "changeHistory": [
    "8c9018d5c7830ae8ec85f446985cafbc8a14d688",
    "3990ffa0834e6b24314a565a92e92d6e8fa37a1e",
    "5cc7873a4723a6c8e8e001d008fcd522eec0433d",
    "2b2465dfac1f147b6bb20d878b69a8cc3e85c8ad",
    "e71d0d87d9b388f211a8eb3d2cd9af347abf9bda"
  ],
  "changeHistoryShort": {
    "8c9018d5c7830ae8ec85f446985cafbc8a14d688": "Ybodychange",
    "3990ffa0834e6b24314a565a92e92d6e8fa37a1e": "Ybodychange",
    "5cc7873a4723a6c8e8e001d008fcd522eec0433d": "Ybodychange",
    "2b2465dfac1f147b6bb20d878b69a8cc3e85c8ad": "Ybodychange",
    "e71d0d87d9b388f211a8eb3d2cd9af347abf9bda": "Yintroduced"
  },
  "changeHistoryDetails": {
    "8c9018d5c7830ae8ec85f446985cafbc8a14d688": {
      "type": "Ybodychange",
      "commitMessage": "YARN-9899. Migration tool that help to generate CS config based on FS config [Phase 2]. Contributed by Peter Bacsko\n",
      "commitDate": "26/11/19 12:22 PM",
      "commitName": "8c9018d5c7830ae8ec85f446985cafbc8a14d688",
      "commitAuthor": "Szilard Nemeth",
      "commitDateOld": "29/10/19 3:24 AM",
      "commitNameOld": "ed45c13f67da06befcd4a70acb16fcf6d844ef2b",
      "commitAuthorOld": "Abhishek Modi",
      "daysBetweenCommits": 28.42,
      "commitsBetweenForRepo": 114,
      "commitsBetweenForFile": 1,
      "diff": "@@ -1,14 +1,8 @@\n   private static void printUsage(PrintStream out) {\n     out.println(\"Usage: yarn resourcemanager [-format-state-store]\");\n     out.println(\"                            \"\n         + \"[-remove-application-from-state-store \u003cappId\u003e]\");\n     out.println(\"                            \"\n         + \"[-format-conf-store]\" + \"\\n\");\n \n-    out.println(\"[-convert-fs-configuration \");\n-    out.println(FSConfigToCSConfigConverter.WARNING_TEXT);\n-    for (CliOption cliOption : CliOption.values()) {\n-      out.println(\"   \" + cliOption.getAsArgumentString());\n-    }\n-    out.println(\"]\");\n   }\n\\ No newline at end of file\n",
      "actualSource": "  private static void printUsage(PrintStream out) {\n    out.println(\"Usage: yarn resourcemanager [-format-state-store]\");\n    out.println(\"                            \"\n        + \"[-remove-application-from-state-store \u003cappId\u003e]\");\n    out.println(\"                            \"\n        + \"[-format-conf-store]\" + \"\\n\");\n\n  }",
      "path": "hadoop-yarn-project/hadoop-yarn/hadoop-yarn-server/hadoop-yarn-server-resourcemanager/src/main/java/org/apache/hadoop/yarn/server/resourcemanager/ResourceManager.java",
      "extendedDetails": {}
    },
    "3990ffa0834e6b24314a565a92e92d6e8fa37a1e": {
      "type": "Ybodychange",
      "commitMessage": "YARN-9909. Offline format of YarnConfigurationStore. Contributed by Prabhu Joseph.\n",
      "commitDate": "16/10/19 6:13 PM",
      "commitName": "3990ffa0834e6b24314a565a92e92d6e8fa37a1e",
      "commitAuthor": "Sunil G",
      "commitDateOld": "14/10/19 8:19 AM",
      "commitNameOld": "5cc7873a4723a6c8e8e001d008fcd522eec0433d",
      "commitAuthorOld": "Szilard Nemeth",
      "daysBetweenCommits": 2.41,
      "commitsBetweenForRepo": 14,
      "commitsBetweenForFile": 1,
      "diff": "@@ -1,12 +1,14 @@\n   private static void printUsage(PrintStream out) {\n     out.println(\"Usage: yarn resourcemanager [-format-state-store]\");\n     out.println(\"                            \"\n-        + \"[-remove-application-from-state-store \u003cappId\u003e]\" + \"\\n\");\n+        + \"[-remove-application-from-state-store \u003cappId\u003e]\");\n+    out.println(\"                            \"\n+        + \"[-format-conf-store]\" + \"\\n\");\n \n     out.println(\"[-convert-fs-configuration \");\n     out.println(FSConfigToCSConfigConverter.WARNING_TEXT);\n     for (CliOption cliOption : CliOption.values()) {\n       out.println(\"   \" + cliOption.getAsArgumentString());\n     }\n     out.println(\"]\");\n   }\n\\ No newline at end of file\n",
      "actualSource": "  private static void printUsage(PrintStream out) {\n    out.println(\"Usage: yarn resourcemanager [-format-state-store]\");\n    out.println(\"                            \"\n        + \"[-remove-application-from-state-store \u003cappId\u003e]\");\n    out.println(\"                            \"\n        + \"[-format-conf-store]\" + \"\\n\");\n\n    out.println(\"[-convert-fs-configuration \");\n    out.println(FSConfigToCSConfigConverter.WARNING_TEXT);\n    for (CliOption cliOption : CliOption.values()) {\n      out.println(\"   \" + cliOption.getAsArgumentString());\n    }\n    out.println(\"]\");\n  }",
      "path": "hadoop-yarn-project/hadoop-yarn/hadoop-yarn-server/hadoop-yarn-server-resourcemanager/src/main/java/org/apache/hadoop/yarn/server/resourcemanager/ResourceManager.java",
      "extendedDetails": {}
    },
    "5cc7873a4723a6c8e8e001d008fcd522eec0433d": {
      "type": "Ybodychange",
      "commitMessage": "YARN-9699. Migration tool that help to generate CS config based on FS config [Phase 1]. Contributed by Peter Bacsko\n",
      "commitDate": "14/10/19 8:19 AM",
      "commitName": "5cc7873a4723a6c8e8e001d008fcd522eec0433d",
      "commitAuthor": "Szilard Nemeth",
      "commitDateOld": "06/09/19 7:18 PM",
      "commitNameOld": "34b82e6da0a471010cdae613ba39487889d79369",
      "commitAuthorOld": "Wangda Tan",
      "daysBetweenCommits": 37.54,
      "commitsBetweenForRepo": 294,
      "commitsBetweenForFile": 1,
      "diff": "@@ -1,5 +1,12 @@\n   private static void printUsage(PrintStream out) {\n     out.println(\"Usage: yarn resourcemanager [-format-state-store]\");\n     out.println(\"                            \"\n         + \"[-remove-application-from-state-store \u003cappId\u003e]\" + \"\\n\");\n+\n+    out.println(\"[-convert-fs-configuration \");\n+    out.println(FSConfigToCSConfigConverter.WARNING_TEXT);\n+    for (CliOption cliOption : CliOption.values()) {\n+      out.println(\"   \" + cliOption.getAsArgumentString());\n+    }\n+    out.println(\"]\");\n   }\n\\ No newline at end of file\n",
      "actualSource": "  private static void printUsage(PrintStream out) {\n    out.println(\"Usage: yarn resourcemanager [-format-state-store]\");\n    out.println(\"                            \"\n        + \"[-remove-application-from-state-store \u003cappId\u003e]\" + \"\\n\");\n\n    out.println(\"[-convert-fs-configuration \");\n    out.println(FSConfigToCSConfigConverter.WARNING_TEXT);\n    for (CliOption cliOption : CliOption.values()) {\n      out.println(\"   \" + cliOption.getAsArgumentString());\n    }\n    out.println(\"]\");\n  }",
      "path": "hadoop-yarn-project/hadoop-yarn/hadoop-yarn-server/hadoop-yarn-server-resourcemanager/src/main/java/org/apache/hadoop/yarn/server/resourcemanager/ResourceManager.java",
      "extendedDetails": {}
    },
    "2b2465dfac1f147b6bb20d878b69a8cc3e85c8ad": {
      "type": "Ybodychange",
      "commitMessage": "YARN-3778. Fix Yarn resourcemanger CLI usage. Contributed by Brahma Reddy Battula\n",
      "commitDate": "08/06/15 3:43 PM",
      "commitName": "2b2465dfac1f147b6bb20d878b69a8cc3e85c8ad",
      "commitAuthor": "Xuan",
      "commitDateOld": "08/05/15 4:23 PM",
      "commitNameOld": "5658998845bbeb3f09037a891f6b254585848de7",
      "commitAuthorOld": "Robert Kanter",
      "daysBetweenCommits": 30.97,
      "commitsBetweenForRepo": 252,
      "commitsBetweenForFile": 1,
      "diff": "@@ -1,5 +1,5 @@\n   private static void printUsage(PrintStream out) {\n-    out.println(\"Usage: java ResourceManager [-format-state-store]\");\n+    out.println(\"Usage: yarn resourcemanager [-format-state-store]\");\n     out.println(\"                            \"\n         + \"[-remove-application-from-state-store \u003cappId\u003e]\" + \"\\n\");\n   }\n\\ No newline at end of file\n",
      "actualSource": "  private static void printUsage(PrintStream out) {\n    out.println(\"Usage: yarn resourcemanager [-format-state-store]\");\n    out.println(\"                            \"\n        + \"[-remove-application-from-state-store \u003cappId\u003e]\" + \"\\n\");\n  }",
      "path": "hadoop-yarn-project/hadoop-yarn/hadoop-yarn-server/hadoop-yarn-server-resourcemanager/src/main/java/org/apache/hadoop/yarn/server/resourcemanager/ResourceManager.java",
      "extendedDetails": {}
    },
    "e71d0d87d9b388f211a8eb3d2cd9af347abf9bda": {
      "type": "Yintroduced",
      "commitMessage": "YARN-3410. YARN admin should be able to remove individual application records from RMStateStore. (Rohith Sharmaks via wangda)\n",
      "commitDate": "21/04/15 5:51 PM",
      "commitName": "e71d0d87d9b388f211a8eb3d2cd9af347abf9bda",
      "commitAuthor": "Wangda Tan",
      "diff": "@@ -0,0 +1,5 @@\n+  private static void printUsage(PrintStream out) {\n+    out.println(\"Usage: java ResourceManager [-format-state-store]\");\n+    out.println(\"                            \"\n+        + \"[-remove-application-from-state-store \u003cappId\u003e]\" + \"\\n\");\n+  }\n\\ No newline at end of file\n",
      "actualSource": "  private static void printUsage(PrintStream out) {\n    out.println(\"Usage: java ResourceManager [-format-state-store]\");\n    out.println(\"                            \"\n        + \"[-remove-application-from-state-store \u003cappId\u003e]\" + \"\\n\");\n  }",
      "path": "hadoop-yarn-project/hadoop-yarn/hadoop-yarn-server/hadoop-yarn-server-resourcemanager/src/main/java/org/apache/hadoop/yarn/server/resourcemanager/ResourceManager.java"
    }
  }
}