{
  "origin": "codeshovel",
  "repositoryName": "hadoop",
  "repositoryPath": "/home/shaiful/research/codeshovel/codeshovel-projects/hadoop/.git",
  "startCommitName": "HEAD",
  "sourceFileName": "FSEditLogOp.java",
  "functionName": "setPath",
  "functionId": "setPath___path-String",
  "sourceFilePath": "hadoop-hdfs-project/hadoop-hdfs/src/main/java/org/apache/hadoop/hdfs/server/namenode/FSEditLogOp.java",
  "functionStartLine": 1526,
  "functionEndLine": 1529,
  "numCommitsSeen": 109,
  "timeTaken": 5192,
  "changeHistory": [
    "37207b75d4b83f7c032dc446d5c7e578f5b7e93a",
    "f79b3e6b17450e9d34c483046b7437b09dd72016",
    "af1ac9a5e8d8d97a855940d853dd59ab4666f6e2",
    "cd7157784e5e5ddc4e77144d042e54dd0d04bac1",
    "d86f3183d93714ba078416af4f609d26376eadb0",
    "438c32aaf9fb0c63f55044cf5ef1b2e0adcf7fea"
  ],
  "changeHistoryShort": {
    "37207b75d4b83f7c032dc446d5c7e578f5b7e93a": "Yreturntypechange",
    "f79b3e6b17450e9d34c483046b7437b09dd72016": "Ymultichange(Yreturntypechange,Ymodifierchange)",
    "af1ac9a5e8d8d97a855940d853dd59ab4666f6e2": "Ymultichange(Yreturntypechange,Ymodifierchange)",
    "cd7157784e5e5ddc4e77144d042e54dd0d04bac1": "Yfilerename",
    "d86f3183d93714ba078416af4f609d26376eadb0": "Yfilerename",
    "438c32aaf9fb0c63f55044cf5ef1b2e0adcf7fea": "Yintroduced"
  },
  "changeHistoryDetails": {
    "37207b75d4b83f7c032dc446d5c7e578f5b7e93a": {
      "type": "Yreturntypechange",
      "commitMessage": "HDFS-6835. Archival Storage: Add a new API to set storage policy. Contributed by Jing Zhao.\n\ngit-svn-id: https://svn.apache.org/repos/asf/hadoop/common/branches/HDFS-6584@1617568 13f79535-47bb-0310-9956-ffa450edef68\n",
      "commitDate": "12/08/14 12:32 PM",
      "commitName": "37207b75d4b83f7c032dc446d5c7e578f5b7e93a",
      "commitAuthor": "Jing Zhao",
      "commitDateOld": "23/07/14 12:05 PM",
      "commitNameOld": "5343b43fd989ec596afed807ddce29ad96c23e2d",
      "commitAuthorOld": "Uma Maheswara Rao G",
      "daysBetweenCommits": 20.02,
      "commitsBetweenForRepo": 135,
      "commitsBetweenForFile": 1,
      "diff": "@@ -1,4 +1,4 @@\n-    ReassignLeaseOp setPath(String path) {\n+    SetStoragePolicyOp setPath(String path) {\n       this.path \u003d path;\n       return this;\n     }\n\\ No newline at end of file\n",
      "actualSource": "    SetStoragePolicyOp setPath(String path) {\n      this.path \u003d path;\n      return this;\n    }",
      "path": "hadoop-hdfs-project/hadoop-hdfs/src/main/java/org/apache/hadoop/hdfs/server/namenode/FSEditLogOp.java",
      "extendedDetails": {
        "oldValue": "ReassignLeaseOp",
        "newValue": "SetStoragePolicyOp"
      }
    },
    "f79b3e6b17450e9d34c483046b7437b09dd72016": {
      "type": "Ymultichange(Yreturntypechange,Ymodifierchange)",
      "commitMessage": "HDFS-5326. add modifyDirective to cacheAdmin (cmccabe)\n\ngit-svn-id: https://svn.apache.org/repos/asf/hadoop/common/trunk@1539839 13f79535-47bb-0310-9956-ffa450edef68\n",
      "commitDate": "07/11/13 2:07 PM",
      "commitName": "f79b3e6b17450e9d34c483046b7437b09dd72016",
      "commitAuthor": "Colin McCabe",
      "subchanges": [
        {
          "type": "Yreturntypechange",
          "commitMessage": "HDFS-5326. add modifyDirective to cacheAdmin (cmccabe)\n\ngit-svn-id: https://svn.apache.org/repos/asf/hadoop/common/trunk@1539839 13f79535-47bb-0310-9956-ffa450edef68\n",
          "commitDate": "07/11/13 2:07 PM",
          "commitName": "f79b3e6b17450e9d34c483046b7437b09dd72016",
          "commitAuthor": "Colin McCabe",
          "commitDateOld": "21/10/13 12:42 PM",
          "commitNameOld": "69e5f90e9febf37d2cdd69c485729c448ac3cabc",
          "commitAuthorOld": "Colin McCabe",
          "daysBetweenCommits": 17.1,
          "commitsBetweenForRepo": 75,
          "commitsBetweenForFile": 1,
          "diff": "@@ -1,4 +1,4 @@\n-    public AddPathBasedCacheDirectiveOp setPath(String path) {\n+    ReassignLeaseOp setPath(String path) {\n       this.path \u003d path;\n       return this;\n     }\n\\ No newline at end of file\n",
          "actualSource": "    ReassignLeaseOp setPath(String path) {\n      this.path \u003d path;\n      return this;\n    }",
          "path": "hadoop-hdfs-project/hadoop-hdfs/src/main/java/org/apache/hadoop/hdfs/server/namenode/FSEditLogOp.java",
          "extendedDetails": {
            "oldValue": "AddPathBasedCacheDirectiveOp",
            "newValue": "ReassignLeaseOp"
          }
        },
        {
          "type": "Ymodifierchange",
          "commitMessage": "HDFS-5326. add modifyDirective to cacheAdmin (cmccabe)\n\ngit-svn-id: https://svn.apache.org/repos/asf/hadoop/common/trunk@1539839 13f79535-47bb-0310-9956-ffa450edef68\n",
          "commitDate": "07/11/13 2:07 PM",
          "commitName": "f79b3e6b17450e9d34c483046b7437b09dd72016",
          "commitAuthor": "Colin McCabe",
          "commitDateOld": "21/10/13 12:42 PM",
          "commitNameOld": "69e5f90e9febf37d2cdd69c485729c448ac3cabc",
          "commitAuthorOld": "Colin McCabe",
          "daysBetweenCommits": 17.1,
          "commitsBetweenForRepo": 75,
          "commitsBetweenForFile": 1,
          "diff": "@@ -1,4 +1,4 @@\n-    public AddPathBasedCacheDirectiveOp setPath(String path) {\n+    ReassignLeaseOp setPath(String path) {\n       this.path \u003d path;\n       return this;\n     }\n\\ No newline at end of file\n",
          "actualSource": "    ReassignLeaseOp setPath(String path) {\n      this.path \u003d path;\n      return this;\n    }",
          "path": "hadoop-hdfs-project/hadoop-hdfs/src/main/java/org/apache/hadoop/hdfs/server/namenode/FSEditLogOp.java",
          "extendedDetails": {
            "oldValue": "[public]",
            "newValue": "[]"
          }
        }
      ]
    },
    "af1ac9a5e8d8d97a855940d853dd59ab4666f6e2": {
      "type": "Ymultichange(Yreturntypechange,Ymodifierchange)",
      "commitMessage": "HDFS-5119. Persist CacheManager state in the edit log. (Contributed by Andrew Wang)\n\ngit-svn-id: https://svn.apache.org/repos/asf/hadoop/common/branches/HDFS-4949@1529238 13f79535-47bb-0310-9956-ffa450edef68\n",
      "commitDate": "04/10/13 10:46 AM",
      "commitName": "af1ac9a5e8d8d97a855940d853dd59ab4666f6e2",
      "commitAuthor": "Andrew Wang",
      "subchanges": [
        {
          "type": "Yreturntypechange",
          "commitMessage": "HDFS-5119. Persist CacheManager state in the edit log. (Contributed by Andrew Wang)\n\ngit-svn-id: https://svn.apache.org/repos/asf/hadoop/common/branches/HDFS-4949@1529238 13f79535-47bb-0310-9956-ffa450edef68\n",
          "commitDate": "04/10/13 10:46 AM",
          "commitName": "af1ac9a5e8d8d97a855940d853dd59ab4666f6e2",
          "commitAuthor": "Andrew Wang",
          "commitDateOld": "30/07/13 12:51 AM",
          "commitNameOld": "8c7a7e619699386f9e6991842558d78aa0c8053d",
          "commitAuthorOld": "Suresh Srinivas",
          "daysBetweenCommits": 66.41,
          "commitsBetweenForRepo": 271,
          "commitsBetweenForFile": 1,
          "diff": "@@ -1,4 +1,4 @@\n-    ReassignLeaseOp setPath(String path) {\n+    public AddPathBasedCacheDirectiveOp setPath(String path) {\n       this.path \u003d path;\n       return this;\n     }\n\\ No newline at end of file\n",
          "actualSource": "    public AddPathBasedCacheDirectiveOp setPath(String path) {\n      this.path \u003d path;\n      return this;\n    }",
          "path": "hadoop-hdfs-project/hadoop-hdfs/src/main/java/org/apache/hadoop/hdfs/server/namenode/FSEditLogOp.java",
          "extendedDetails": {
            "oldValue": "ReassignLeaseOp",
            "newValue": "AddPathBasedCacheDirectiveOp"
          }
        },
        {
          "type": "Ymodifierchange",
          "commitMessage": "HDFS-5119. Persist CacheManager state in the edit log. (Contributed by Andrew Wang)\n\ngit-svn-id: https://svn.apache.org/repos/asf/hadoop/common/branches/HDFS-4949@1529238 13f79535-47bb-0310-9956-ffa450edef68\n",
          "commitDate": "04/10/13 10:46 AM",
          "commitName": "af1ac9a5e8d8d97a855940d853dd59ab4666f6e2",
          "commitAuthor": "Andrew Wang",
          "commitDateOld": "30/07/13 12:51 AM",
          "commitNameOld": "8c7a7e619699386f9e6991842558d78aa0c8053d",
          "commitAuthorOld": "Suresh Srinivas",
          "daysBetweenCommits": 66.41,
          "commitsBetweenForRepo": 271,
          "commitsBetweenForFile": 1,
          "diff": "@@ -1,4 +1,4 @@\n-    ReassignLeaseOp setPath(String path) {\n+    public AddPathBasedCacheDirectiveOp setPath(String path) {\n       this.path \u003d path;\n       return this;\n     }\n\\ No newline at end of file\n",
          "actualSource": "    public AddPathBasedCacheDirectiveOp setPath(String path) {\n      this.path \u003d path;\n      return this;\n    }",
          "path": "hadoop-hdfs-project/hadoop-hdfs/src/main/java/org/apache/hadoop/hdfs/server/namenode/FSEditLogOp.java",
          "extendedDetails": {
            "oldValue": "[]",
            "newValue": "[public]"
          }
        }
      ]
    },
    "cd7157784e5e5ddc4e77144d042e54dd0d04bac1": {
      "type": "Yfilerename",
      "commitMessage": "HADOOP-7560. Change src layout to be heirarchical. Contributed by Alejandro Abdelnur.\n\n\ngit-svn-id: https://svn.apache.org/repos/asf/hadoop/common/trunk@1161332 13f79535-47bb-0310-9956-ffa450edef68\n",
      "commitDate": "24/08/11 5:14 PM",
      "commitName": "cd7157784e5e5ddc4e77144d042e54dd0d04bac1",
      "commitAuthor": "Arun Murthy",
      "commitDateOld": "24/08/11 5:06 PM",
      "commitNameOld": "bb0005cfec5fd2861600ff5babd259b48ba18b63",
      "commitAuthorOld": "Arun Murthy",
      "daysBetweenCommits": 0.01,
      "commitsBetweenForRepo": 1,
      "commitsBetweenForFile": 1,
      "diff": "",
      "actualSource": "    ReassignLeaseOp setPath(String path) {\n      this.path \u003d path;\n      return this;\n    }",
      "path": "hadoop-hdfs-project/hadoop-hdfs/src/main/java/org/apache/hadoop/hdfs/server/namenode/FSEditLogOp.java",
      "extendedDetails": {
        "oldPath": "hadoop-hdfs/src/main/java/org/apache/hadoop/hdfs/server/namenode/FSEditLogOp.java",
        "newPath": "hadoop-hdfs-project/hadoop-hdfs/src/main/java/org/apache/hadoop/hdfs/server/namenode/FSEditLogOp.java"
      }
    },
    "d86f3183d93714ba078416af4f609d26376eadb0": {
      "type": "Yfilerename",
      "commitMessage": "HDFS-2096. Mavenization of hadoop-hdfs. Contributed by Alejandro Abdelnur.\n\ngit-svn-id: https://svn.apache.org/repos/asf/hadoop/common/trunk@1159702 13f79535-47bb-0310-9956-ffa450edef68\n",
      "commitDate": "19/08/11 10:36 AM",
      "commitName": "d86f3183d93714ba078416af4f609d26376eadb0",
      "commitAuthor": "Thomas White",
      "commitDateOld": "19/08/11 10:26 AM",
      "commitNameOld": "6ee5a73e0e91a2ef27753a32c576835e951d8119",
      "commitAuthorOld": "Thomas White",
      "daysBetweenCommits": 0.01,
      "commitsBetweenForRepo": 1,
      "commitsBetweenForFile": 1,
      "diff": "",
      "actualSource": "    ReassignLeaseOp setPath(String path) {\n      this.path \u003d path;\n      return this;\n    }",
      "path": "hadoop-hdfs/src/main/java/org/apache/hadoop/hdfs/server/namenode/FSEditLogOp.java",
      "extendedDetails": {
        "oldPath": "hdfs/src/java/org/apache/hadoop/hdfs/server/namenode/FSEditLogOp.java",
        "newPath": "hadoop-hdfs/src/main/java/org/apache/hadoop/hdfs/server/namenode/FSEditLogOp.java"
      }
    },
    "438c32aaf9fb0c63f55044cf5ef1b2e0adcf7fea": {
      "type": "Yintroduced",
      "commitMessage": "HDFS-2149. Move EditLogOp serialization formats into FsEditLogOp implementations. Contributed by Ivan Kelly.\n\ngit-svn-id: https://svn.apache.org/repos/asf/hadoop/common/trunk@1151238 13f79535-47bb-0310-9956-ffa450edef68\n",
      "commitDate": "26/07/11 1:46 PM",
      "commitName": "438c32aaf9fb0c63f55044cf5ef1b2e0adcf7fea",
      "commitAuthor": "Todd Lipcon",
      "diff": "@@ -0,0 +1,4 @@\n+    ReassignLeaseOp setPath(String path) {\n+      this.path \u003d path;\n+      return this;\n+    }\n\\ No newline at end of file\n",
      "actualSource": "    ReassignLeaseOp setPath(String path) {\n      this.path \u003d path;\n      return this;\n    }",
      "path": "hdfs/src/java/org/apache/hadoop/hdfs/server/namenode/FSEditLogOp.java"
    }
  }
}