{
  "origin": "codeshovel",
  "repositoryName": "hadoop",
  "repositoryPath": "/home/shaiful/research/codeshovel/codeshovel-projects/hadoop/.git",
  "startCommitName": "HEAD",
  "sourceFileName": "UserGroupInformation.java",
  "functionName": "prependFileAuthority",
  "functionId": "prependFileAuthority___keytabPath-String",
  "sourceFilePath": "hadoop-common-project/hadoop-common/src/main/java/org/apache/hadoop/security/UserGroupInformation.java",
  "functionStartLine": 2170,
  "functionEndLine": 2174,
  "numCommitsSeen": 104,
  "timeTaken": 2150,
  "changeHistory": [
    "411bb0bd991344c0cd01bda1de27962f0470e944"
  ],
  "changeHistoryShort": {
    "411bb0bd991344c0cd01bda1de27962f0470e944": "Yintroduced"
  },
  "changeHistoryDetails": {
    "411bb0bd991344c0cd01bda1de27962f0470e944": {
      "type": "Yintroduced",
      "commitMessage": "HADOOP-9283. Add support for running the Hadoop client on AIX. Contributed by Aaron T. Myers.\n\n\ngit-svn-id: https://svn.apache.org/repos/asf/hadoop/common/trunk@1443303 13f79535-47bb-0310-9956-ffa450edef68\n",
      "commitDate": "06/02/13 7:13 PM",
      "commitName": "411bb0bd991344c0cd01bda1de27962f0470e944",
      "commitAuthor": "Aaron Myers",
      "diff": "@@ -0,0 +1,4 @@\n+  private static String prependFileAuthority(String keytabPath) {\n+    return keytabPath.startsWith(\"file://\") ? keytabPath\n+        : \"file://\" + keytabPath;\n+  }\n\\ No newline at end of file\n",
      "actualSource": "  private static String prependFileAuthority(String keytabPath) {\n    return keytabPath.startsWith(\"file://\") ? keytabPath\n        : \"file://\" + keytabPath;\n  }",
      "path": "hadoop-common-project/hadoop-common/src/main/java/org/apache/hadoop/security/UserGroupInformation.java"
    }
  }
}