{
  "origin": "codeshovel",
  "repositoryName": "checkstyle",
  "repositoryPath": "/home/shaiful/research/codeshovel/codeshovel-projects/checkstyle/.git",
  "startCommitName": "HEAD",
  "sourceFileName": "CsvFilterElement.java",
  "functionName": "equals",
  "functionId": "equals___object-Object",
  "sourceFilePath": "src/main/java/com/puppycrawl/tools/checkstyle/filters/CsvFilterElement.java",
  "functionStartLine": 105,
  "functionEndLine": 114,
  "numCommitsSeen": 60,
  "timeTaken": 2270,
  "changeHistory": [
    "738b09af0b927e53865ac9f4049203e5f8a38310",
    "f60a9cfe8b1b27d5ea25095bdfc690001da9f4d6",
    "cf5851ed2977d062777a16d013b4b8ec24d73ffc",
    "5cfe30d7ad6b98069f66ac2494afdcebcbcc8f1d",
    "f1efb27670a93690577f1bae17fc9dcbd88a795d",
    "889f470ea6ca16b3067e35e2463282d9678f7bf0",
    "8d242382f8bb77488b6da23bdd0d2d61583703fc"
  ],
  "changeHistoryShort": {
    "738b09af0b927e53865ac9f4049203e5f8a38310": "Ymultichange(Yfilerename,Ybodychange)",
    "f60a9cfe8b1b27d5ea25095bdfc690001da9f4d6": "Ymultichange(Yfilerename,Ybodychange)",
    "cf5851ed2977d062777a16d013b4b8ec24d73ffc": "Ybodychange",
    "5cfe30d7ad6b98069f66ac2494afdcebcbcc8f1d": "Ymultichange(Yparameterchange,Ybodychange)",
    "f1efb27670a93690577f1bae17fc9dcbd88a795d": "Yfilerename",
    "889f470ea6ca16b3067e35e2463282d9678f7bf0": "Ybodychange",
    "8d242382f8bb77488b6da23bdd0d2d61583703fc": "Yintroduced"
  },
  "changeHistoryDetails": {
    "738b09af0b927e53865ac9f4049203e5f8a38310": {
      "type": "Ymultichange(Yfilerename,Ybodychange)",
      "commitMessage": "Issue #4978: renamed sub-children filters to filter element",
      "commitDate": "18/02/19 2:12 PM",
      "commitName": "738b09af0b927e53865ac9f4049203e5f8a38310",
      "commitAuthor": "rnveach",
      "subchanges": [
        {
          "type": "Yfilerename",
          "commitMessage": "Issue #4978: renamed sub-children filters to filter element",
          "commitDate": "18/02/19 2:12 PM",
          "commitName": "738b09af0b927e53865ac9f4049203e5f8a38310",
          "commitAuthor": "rnveach",
          "commitDateOld": "18/02/19 8:27 AM",
          "commitNameOld": "287e1edc41038cdcceb463b4bf77af363f73854e",
          "commitAuthorOld": "WANG CHAO",
          "daysBetweenCommits": 0.24,
          "commitsBetweenForRepo": 1,
          "commitsBetweenForFile": 1,
          "diff": "@@ -1,10 +1,10 @@\n     public boolean equals(Object object) {\n         if (this \u003d\u003d object) {\n             return true;\n         }\n         if (object \u003d\u003d null || getClass() !\u003d object.getClass()) {\n             return false;\n         }\n-        final CsvFilter csvFilter \u003d (CsvFilter) object;\n+        final CsvFilterElement csvFilter \u003d (CsvFilterElement) object;\n         return Objects.equals(filters, csvFilter.filters);\n     }\n\\ No newline at end of file\n",
          "actualSource": "    public boolean equals(Object object) {\n        if (this \u003d\u003d object) {\n            return true;\n        }\n        if (object \u003d\u003d null || getClass() !\u003d object.getClass()) {\n            return false;\n        }\n        final CsvFilterElement csvFilter \u003d (CsvFilterElement) object;\n        return Objects.equals(filters, csvFilter.filters);\n    }",
          "path": "src/main/java/com/puppycrawl/tools/checkstyle/filters/CsvFilterElement.java",
          "extendedDetails": {
            "oldPath": "src/main/java/com/puppycrawl/tools/checkstyle/filters/CsvFilter.java",
            "newPath": "src/main/java/com/puppycrawl/tools/checkstyle/filters/CsvFilterElement.java"
          }
        },
        {
          "type": "Ybodychange",
          "commitMessage": "Issue #4978: renamed sub-children filters to filter element",
          "commitDate": "18/02/19 2:12 PM",
          "commitName": "738b09af0b927e53865ac9f4049203e5f8a38310",
          "commitAuthor": "rnveach",
          "commitDateOld": "18/02/19 8:27 AM",
          "commitNameOld": "287e1edc41038cdcceb463b4bf77af363f73854e",
          "commitAuthorOld": "WANG CHAO",
          "daysBetweenCommits": 0.24,
          "commitsBetweenForRepo": 1,
          "commitsBetweenForFile": 1,
          "diff": "@@ -1,10 +1,10 @@\n     public boolean equals(Object object) {\n         if (this \u003d\u003d object) {\n             return true;\n         }\n         if (object \u003d\u003d null || getClass() !\u003d object.getClass()) {\n             return false;\n         }\n-        final CsvFilter csvFilter \u003d (CsvFilter) object;\n+        final CsvFilterElement csvFilter \u003d (CsvFilterElement) object;\n         return Objects.equals(filters, csvFilter.filters);\n     }\n\\ No newline at end of file\n",
          "actualSource": "    public boolean equals(Object object) {\n        if (this \u003d\u003d object) {\n            return true;\n        }\n        if (object \u003d\u003d null || getClass() !\u003d object.getClass()) {\n            return false;\n        }\n        final CsvFilterElement csvFilter \u003d (CsvFilterElement) object;\n        return Objects.equals(filters, csvFilter.filters);\n    }",
          "path": "src/main/java/com/puppycrawl/tools/checkstyle/filters/CsvFilterElement.java",
          "extendedDetails": {}
        }
      ]
    },
    "f60a9cfe8b1b27d5ea25095bdfc690001da9f4d6": {
      "type": "Ymultichange(Yfilerename,Ybodychange)",
      "commitMessage": "Issue #2639: CSV is removed from allowed abbreviations\n",
      "commitDate": "25/11/15 11:01 AM",
      "commitName": "f60a9cfe8b1b27d5ea25095bdfc690001da9f4d6",
      "commitAuthor": "Roman Ivanov",
      "subchanges": [
        {
          "type": "Yfilerename",
          "commitMessage": "Issue #2639: CSV is removed from allowed abbreviations\n",
          "commitDate": "25/11/15 11:01 AM",
          "commitName": "f60a9cfe8b1b27d5ea25095bdfc690001da9f4d6",
          "commitAuthor": "Roman Ivanov",
          "commitDateOld": "25/11/15 10:36 AM",
          "commitNameOld": "3a55941f33dcd9111d6b61b0505217f47973a39d",
          "commitAuthorOld": "Roman Ivanov",
          "daysBetweenCommits": 0.02,
          "commitsBetweenForRepo": 1,
          "commitsBetweenForFile": 1,
          "diff": "@@ -1,10 +1,10 @@\n     public boolean equals(Object object) {\n         if (this \u003d\u003d object) {\n             return true;\n         }\n         if (object \u003d\u003d null || getClass() !\u003d object.getClass()) {\n             return false;\n         }\n-        final CSVFilter csvFilter \u003d (CSVFilter) object;\n+        final CsvFilter csvFilter \u003d (CsvFilter) object;\n         return Objects.equals(filters, csvFilter.filters);\n     }\n\\ No newline at end of file\n",
          "actualSource": "    public boolean equals(Object object) {\n        if (this \u003d\u003d object) {\n            return true;\n        }\n        if (object \u003d\u003d null || getClass() !\u003d object.getClass()) {\n            return false;\n        }\n        final CsvFilter csvFilter \u003d (CsvFilter) object;\n        return Objects.equals(filters, csvFilter.filters);\n    }",
          "path": "src/main/java/com/puppycrawl/tools/checkstyle/filters/CsvFilter.java",
          "extendedDetails": {
            "oldPath": "src/main/java/com/puppycrawl/tools/checkstyle/filters/CSVFilter.java",
            "newPath": "src/main/java/com/puppycrawl/tools/checkstyle/filters/CsvFilter.java"
          }
        },
        {
          "type": "Ybodychange",
          "commitMessage": "Issue #2639: CSV is removed from allowed abbreviations\n",
          "commitDate": "25/11/15 11:01 AM",
          "commitName": "f60a9cfe8b1b27d5ea25095bdfc690001da9f4d6",
          "commitAuthor": "Roman Ivanov",
          "commitDateOld": "25/11/15 10:36 AM",
          "commitNameOld": "3a55941f33dcd9111d6b61b0505217f47973a39d",
          "commitAuthorOld": "Roman Ivanov",
          "daysBetweenCommits": 0.02,
          "commitsBetweenForRepo": 1,
          "commitsBetweenForFile": 1,
          "diff": "@@ -1,10 +1,10 @@\n     public boolean equals(Object object) {\n         if (this \u003d\u003d object) {\n             return true;\n         }\n         if (object \u003d\u003d null || getClass() !\u003d object.getClass()) {\n             return false;\n         }\n-        final CSVFilter csvFilter \u003d (CSVFilter) object;\n+        final CsvFilter csvFilter \u003d (CsvFilter) object;\n         return Objects.equals(filters, csvFilter.filters);\n     }\n\\ No newline at end of file\n",
          "actualSource": "    public boolean equals(Object object) {\n        if (this \u003d\u003d object) {\n            return true;\n        }\n        if (object \u003d\u003d null || getClass() !\u003d object.getClass()) {\n            return false;\n        }\n        final CsvFilter csvFilter \u003d (CsvFilter) object;\n        return Objects.equals(filters, csvFilter.filters);\n    }",
          "path": "src/main/java/com/puppycrawl/tools/checkstyle/filters/CsvFilter.java",
          "extendedDetails": {}
        }
      ]
    },
    "cf5851ed2977d062777a16d013b4b8ec24d73ffc": {
      "type": "Ybodychange",
      "commitMessage": "Use EqualsVerifier to test CSVFilter. #1088\n",
      "commitDate": "18/05/15 5:56 AM",
      "commitName": "cf5851ed2977d062777a16d013b4b8ec24d73ffc",
      "commitAuthor": "Michal Kordas",
      "commitDateOld": "17/05/15 4:47 AM",
      "commitNameOld": "0f58857d73933c7b6b7e62f0c7c16ad7af51556f",
      "commitAuthorOld": "Michal Kordas",
      "daysBetweenCommits": 1.05,
      "commitsBetweenForRepo": 4,
      "commitsBetweenForFile": 1,
      "diff": "@@ -1,7 +1,10 @@\n     public boolean equals(Object object) {\n-        if (object instanceof CSVFilter) {\n-            final CSVFilter other \u003d (CSVFilter) object;\n-            return this.filters.equals(other.filters);\n+        if (this \u003d\u003d object) {\n+            return true;\n         }\n-        return false;\n+        if (object \u003d\u003d null || getClass() !\u003d object.getClass()) {\n+            return false;\n+        }\n+        final CSVFilter csvFilter \u003d (CSVFilter) object;\n+        return Objects.equals(filters, csvFilter.filters);\n     }\n\\ No newline at end of file\n",
      "actualSource": "    public boolean equals(Object object) {\n        if (this \u003d\u003d object) {\n            return true;\n        }\n        if (object \u003d\u003d null || getClass() !\u003d object.getClass()) {\n            return false;\n        }\n        final CSVFilter csvFilter \u003d (CSVFilter) object;\n        return Objects.equals(filters, csvFilter.filters);\n    }",
      "path": "src/main/java/com/puppycrawl/tools/checkstyle/filters/CSVFilter.java",
      "extendedDetails": {}
    },
    "5cfe30d7ad6b98069f66ac2494afdcebcbcc8f1d": {
      "type": "Ymultichange(Yparameterchange,Ybodychange)",
      "commitMessage": "Prefixes, filters, #512\n",
      "commitDate": "19/01/15 6:20 AM",
      "commitName": "5cfe30d7ad6b98069f66ac2494afdcebcbcc8f1d",
      "commitAuthor": "alexkravin",
      "subchanges": [
        {
          "type": "Yparameterchange",
          "commitMessage": "Prefixes, filters, #512\n",
          "commitDate": "19/01/15 6:20 AM",
          "commitName": "5cfe30d7ad6b98069f66ac2494afdcebcbcc8f1d",
          "commitAuthor": "alexkravin",
          "commitDateOld": "14/12/14 10:33 PM",
          "commitNameOld": "7aa061665c2b005f97b0c05bf03604636175dc9a",
          "commitAuthorOld": "Michal Kordas",
          "daysBetweenCommits": 35.32,
          "commitsBetweenForRepo": 76,
          "commitsBetweenForFile": 1,
          "diff": "@@ -1,8 +1,8 @@\n-    public boolean equals(Object aObject)\n+    public boolean equals(Object object)\n     {\n-        if (aObject instanceof CSVFilter) {\n-            final CSVFilter other \u003d (CSVFilter) aObject;\n-            return this.mFilters.equals(other.mFilters);\n+        if (object instanceof CSVFilter) {\n+            final CSVFilter other \u003d (CSVFilter) object;\n+            return this.filters.equals(other.filters);\n         }\n         return false;\n     }\n\\ No newline at end of file\n",
          "actualSource": "    public boolean equals(Object object)\n    {\n        if (object instanceof CSVFilter) {\n            final CSVFilter other \u003d (CSVFilter) object;\n            return this.filters.equals(other.filters);\n        }\n        return false;\n    }",
          "path": "src/main/java/com/puppycrawl/tools/checkstyle/filters/CSVFilter.java",
          "extendedDetails": {
            "oldValue": "[aObject-Object]",
            "newValue": "[object-Object]"
          }
        },
        {
          "type": "Ybodychange",
          "commitMessage": "Prefixes, filters, #512\n",
          "commitDate": "19/01/15 6:20 AM",
          "commitName": "5cfe30d7ad6b98069f66ac2494afdcebcbcc8f1d",
          "commitAuthor": "alexkravin",
          "commitDateOld": "14/12/14 10:33 PM",
          "commitNameOld": "7aa061665c2b005f97b0c05bf03604636175dc9a",
          "commitAuthorOld": "Michal Kordas",
          "daysBetweenCommits": 35.32,
          "commitsBetweenForRepo": 76,
          "commitsBetweenForFile": 1,
          "diff": "@@ -1,8 +1,8 @@\n-    public boolean equals(Object aObject)\n+    public boolean equals(Object object)\n     {\n-        if (aObject instanceof CSVFilter) {\n-            final CSVFilter other \u003d (CSVFilter) aObject;\n-            return this.mFilters.equals(other.mFilters);\n+        if (object instanceof CSVFilter) {\n+            final CSVFilter other \u003d (CSVFilter) object;\n+            return this.filters.equals(other.filters);\n         }\n         return false;\n     }\n\\ No newline at end of file\n",
          "actualSource": "    public boolean equals(Object object)\n    {\n        if (object instanceof CSVFilter) {\n            final CSVFilter other \u003d (CSVFilter) object;\n            return this.filters.equals(other.filters);\n        }\n        return false;\n    }",
          "path": "src/main/java/com/puppycrawl/tools/checkstyle/filters/CSVFilter.java",
          "extendedDetails": {}
        }
      ]
    },
    "f1efb27670a93690577f1bae17fc9dcbd88a795d": {
      "type": "Yfilerename",
      "commitMessage": "moving to standard directory layout\n",
      "commitDate": "04/03/14 9:18 AM",
      "commitName": "f1efb27670a93690577f1bae17fc9dcbd88a795d",
      "commitAuthor": "Ivan Sopov",
      "commitDateOld": "26/02/14 10:35 PM",
      "commitNameOld": "1cdaeaaa4fbf02a7388f1fcbea1c86ef0ea32fed",
      "commitAuthorOld": "Andrew Gaul",
      "daysBetweenCommits": 5.45,
      "commitsBetweenForRepo": 1,
      "commitsBetweenForFile": 1,
      "diff": "",
      "actualSource": "    public boolean equals(Object aObject)\n    {\n        if (aObject instanceof CSVFilter) {\n            final CSVFilter other \u003d (CSVFilter) aObject;\n            return this.mFilters.equals(other.mFilters);\n        }\n        return false;\n    }",
      "path": "src/main/java/com/puppycrawl/tools/checkstyle/filters/CSVFilter.java",
      "extendedDetails": {
        "oldPath": "src/checkstyle/com/puppycrawl/tools/checkstyle/filters/CSVFilter.java",
        "newPath": "src/main/java/com/puppycrawl/tools/checkstyle/filters/CSVFilter.java"
      }
    },
    "889f470ea6ca16b3067e35e2463282d9678f7bf0": {
      "type": "Ybodychange",
      "commitMessage": "General cleanup\n",
      "commitDate": "21/07/04 4:15 AM",
      "commitName": "889f470ea6ca16b3067e35e2463282d9678f7bf0",
      "commitAuthor": "Oliver Burn",
      "commitDateOld": "20/01/04 5:23 PM",
      "commitNameOld": "9e5fe92b7cfbfd61db3312c1085215c79511ba2a",
      "commitAuthorOld": "Rick Giles",
      "daysBetweenCommits": 182.41,
      "commitsBetweenForRepo": 109,
      "commitsBetweenForFile": 1,
      "diff": "@@ -1,10 +1,8 @@\n     public boolean equals(Object aObject)\n     {\n         if (aObject instanceof CSVFilter) {\n             final CSVFilter other \u003d (CSVFilter) aObject;\n             return this.mFilters.equals(other.mFilters);\n         }\n-        else {\n-            return false;\n-        }\n+        return false;\n     }\n\\ No newline at end of file\n",
      "actualSource": "    public boolean equals(Object aObject)\n    {\n        if (aObject instanceof CSVFilter) {\n            final CSVFilter other \u003d (CSVFilter) aObject;\n            return this.mFilters.equals(other.mFilters);\n        }\n        return false;\n    }",
      "path": "src/checkstyle/com/puppycrawl/tools/checkstyle/filters/CSVFilter.java",
      "extendedDetails": {}
    },
    "8d242382f8bb77488b6da23bdd0d2d61583703fc": {
      "type": "Yintroduced",
      "commitMessage": "Filter.accept() now takes AuditEvent, not an Object.\n",
      "commitDate": "06/11/03 8:49 PM",
      "commitName": "8d242382f8bb77488b6da23bdd0d2d61583703fc",
      "commitAuthor": "Oleg Sukhodolsky",
      "diff": "@@ -0,0 +1,10 @@\n+    public boolean equals (Object aObject)\n+    {\n+        if (aObject instanceof CSVFilter) {\n+            final CSVFilter other \u003d (CSVFilter) aObject;\n+            return this.mFilters.equals(other.mFilters);\n+        }\n+        else {\n+            return false;\n+        }\n+    }\n\\ No newline at end of file\n",
      "actualSource": "    public boolean equals (Object aObject)\n    {\n        if (aObject instanceof CSVFilter) {\n            final CSVFilter other \u003d (CSVFilter) aObject;\n            return this.mFilters.equals(other.mFilters);\n        }\n        else {\n            return false;\n        }\n    }",
      "path": "src/checkstyle/com/puppycrawl/tools/checkstyle/filters/CSVFilter.java"
    }
  }
}